<annotation>
	<folder></folder>
	<filename>1188_jpg.rf.1ae54431138ee2e14543f2f90ae09c6b.jpg</filename>
	<path>1188_jpg.rf.1ae54431138ee2e14543f2f90ae09c6b.jpg</path>
	<source>
		<database>roboflow.ai</database>
	</source>
	<size>
		<width>416</width>
		<height>550</height>
		<depth>3</depth>
	</size>
	<segmented>0</segmented>
	<object>
		<name>Cocos</name>
		<pose>Unspecified</pose>
		<truncated>0</truncated>
		<difficult>0</difficult>
		<occluded>0</occluded>
		<bndbox>
			<xmin>244</xmin>
			<xmax>329</xmax>
			<ymin>65</ymin>
			<ymax>150</ymax>
		</bndbox>
	</object>
	<object>
		<name>Pomegranate</name>
		<pose>Unspecified</pose>
		<truncated>0</truncated>
		<difficult>0</difficult>
		<occluded>0</occluded>
		<bndbox>
			<xmin>153</xmin>
			<xmax>275</xmax>
			<ymin>218</ymin>
			<ymax>340</ymax>
		</bndbox>
	</object>
	<object>
		<name>Cantaloupe</name>
		<pose>Unspecified</pose>
		<truncated>0</truncated>
		<difficult>0</difficult>
		<occluded>0</occluded>
		<bndbox>
			<xmin>24</xmin>
			<xmax>159</xmax>
			<ymin>222</ymin>
			<ymax>357</ymax>
		</bndbox>
	</object>
	<object>
		<name>Passion</name>
		<pose>Unspecified</pose>
		<truncated>0</truncated>
		<difficult>0</difficult>
		<occluded>0</occluded>
		<bndbox>
			<xmin>352</xmin>
			<xmax>408</xmax>
			<ymin>27</ymin>
			<ymax>83</ymax>
		</bndbox>
	</object>
</annotation>
