<annotation>
	<folder></folder>
	<filename>1307_jpg.rf.9a7de36203238eb3c6a16f2354730e55.jpg</filename>
	<path>1307_jpg.rf.9a7de36203238eb3c6a16f2354730e55.jpg</path>
	<source>
		<database>roboflow.ai</database>
	</source>
	<size>
		<width>416</width>
		<height>550</height>
		<depth>3</depth>
	</size>
	<segmented>0</segmented>
	<object>
		<name>Huckleberry</name>
		<pose>Unspecified</pose>
		<truncated>0</truncated>
		<difficult>0</difficult>
		<occluded>0</occluded>
		<bndbox>
			<xmin>34</xmin>
			<xmax>147</xmax>
			<ymin>10</ymin>
			<ymax>123</ymax>
		</bndbox>
	</object>
	<object>
		<name>Rambutan</name>
		<pose>Unspecified</pose>
		<truncated>0</truncated>
		<difficult>0</difficult>
		<occluded>0</occluded>
		<bndbox>
			<xmin>145</xmin>
			<xmax>230</xmax>
			<ymin>425</ymin>
			<ymax>510</ymax>
		</bndbox>
	</object>
	<object>
		<name>Cactus</name>
		<pose>Unspecified</pose>
		<truncated>0</truncated>
		<difficult>0</difficult>
		<occluded>0</occluded>
		<bndbox>
			<xmin>81</xmin>
			<xmax>163</xmax>
			<ymin>81</ymin>
			<ymax>163</ymax>
		</bndbox>
	</object>
</annotation>
