<annotation>
	<folder></folder>
	<filename>1411_jpg.rf.c2b193ee3ed7ed3354e5be4b993c83bb.jpg</filename>
	<path>1411_jpg.rf.c2b193ee3ed7ed3354e5be4b993c83bb.jpg</path>
	<source>
		<database>roboflow.ai</database>
	</source>
	<size>
		<width>416</width>
		<height>550</height>
		<depth>3</depth>
	</size>
	<segmented>0</segmented>
	<object>
		<name>Mandarine</name>
		<pose>Unspecified</pose>
		<truncated>0</truncated>
		<difficult>0</difficult>
		<occluded>0</occluded>
		<bndbox>
			<xmin>78</xmin>
			<xmax>151</xmax>
			<ymin>470</ymin>
			<ymax>543</ymax>
		</bndbox>
	</object>
</annotation>
