<annotation>
	<folder></folder>
	<filename>1442_jpg.rf.a17fe819008b0d5c40173c0dafb8a6dd.jpg</filename>
	<path>1442_jpg.rf.a17fe819008b0d5c40173c0dafb8a6dd.jpg</path>
	<source>
		<database>roboflow.ai</database>
	</source>
	<size>
		<width>416</width>
		<height>550</height>
		<depth>3</depth>
	</size>
	<segmented>0</segmented>
	<object>
		<name>Cherry</name>
		<pose>Unspecified</pose>
		<truncated>0</truncated>
		<difficult>0</difficult>
		<occluded>0</occluded>
		<bndbox>
			<xmin>37</xmin>
			<xmax>108</xmax>
			<ymin>191</ymin>
			<ymax>262</ymax>
		</bndbox>
	</object>
	<object>
		<name>Onion</name>
		<pose>Unspecified</pose>
		<truncated>0</truncated>
		<difficult>0</difficult>
		<occluded>0</occluded>
		<bndbox>
			<xmin>5</xmin>
			<xmax>70</xmax>
			<ymin>275</ymin>
			<ymax>340</ymax>
		</bndbox>
	</object>
</annotation>
