<annotation>
	<folder></folder>
	<filename>1716_jpg.rf.de361cfd1829d96f3e75fb45930d1736.jpg</filename>
	<path>1716_jpg.rf.de361cfd1829d96f3e75fb45930d1736.jpg</path>
	<source>
		<database>roboflow.ai</database>
	</source>
	<size>
		<width>416</width>
		<height>550</height>
		<depth>3</depth>
	</size>
	<segmented>0</segmented>
	<object>
		<name>Quince</name>
		<pose>Unspecified</pose>
		<truncated>0</truncated>
		<difficult>0</difficult>
		<occluded>0</occluded>
		<bndbox>
			<xmin>292</xmin>
			<xmax>401</xmax>
			<ymin>60</ymin>
			<ymax>169</ymax>
		</bndbox>
	</object>
	<object>
		<name>Guava</name>
		<pose>Unspecified</pose>
		<truncated>0</truncated>
		<difficult>0</difficult>
		<occluded>0</occluded>
		<bndbox>
			<xmin>59</xmin>
			<xmax>135</xmax>
			<ymin>160</ymin>
			<ymax>236</ymax>
		</bndbox>
	</object>
</annotation>
