<annotation>
	<folder></folder>
	<filename>1800_jpg.rf.1e71878178312ac949694c2afd89d0b3.jpg</filename>
	<path>1800_jpg.rf.1e71878178312ac949694c2afd89d0b3.jpg</path>
	<source>
		<database>roboflow.ai</database>
	</source>
	<size>
		<width>416</width>
		<height>550</height>
		<depth>3</depth>
	</size>
	<segmented>0</segmented>
	<object>
		<name>Guava</name>
		<pose>Unspecified</pose>
		<truncated>0</truncated>
		<difficult>0</difficult>
		<occluded>0</occluded>
		<bndbox>
			<xmin>12</xmin>
			<xmax>151</xmax>
			<ymin>154</ymin>
			<ymax>293</ymax>
		</bndbox>
	</object>
	<object>
		<name>Beetroot</name>
		<pose>Unspecified</pose>
		<truncated>0</truncated>
		<difficult>0</difficult>
		<occluded>0</occluded>
		<bndbox>
			<xmin>188</xmin>
			<xmax>337</xmax>
			<ymin>367</ymin>
			<ymax>516</ymax>
		</bndbox>
	</object>
	<object>
		<name>Limes</name>
		<pose>Unspecified</pose>
		<truncated>0</truncated>
		<difficult>0</difficult>
		<occluded>0</occluded>
		<bndbox>
			<xmin>105</xmin>
			<xmax>223</xmax>
			<ymin>326</ymin>
			<ymax>444</ymax>
		</bndbox>
	</object>
</annotation>
