<annotation>
	<folder></folder>
	<filename>2063_jpg.rf.1697b4bcc2d9972dbd250ad3805d0675.jpg</filename>
	<path>2063_jpg.rf.1697b4bcc2d9972dbd250ad3805d0675.jpg</path>
	<source>
		<database>roboflow.ai</database>
	</source>
	<size>
		<width>416</width>
		<height>550</height>
		<depth>3</depth>
	</size>
	<segmented>0</segmented>
	<object>
		<name>Avocado</name>
		<pose>Unspecified</pose>
		<truncated>0</truncated>
		<difficult>0</difficult>
		<occluded>0</occluded>
		<bndbox>
			<xmin>271</xmin>
			<xmax>386</xmax>
			<ymin>71</ymin>
			<ymax>186</ymax>
		</bndbox>
	</object>
	<object>
		<name>Blueberry</name>
		<pose>Unspecified</pose>
		<truncated>0</truncated>
		<difficult>0</difficult>
		<occluded>0</occluded>
		<bndbox>
			<xmin>261</xmin>
			<xmax>385</xmax>
			<ymin>151</ymin>
			<ymax>275</ymax>
		</bndbox>
	</object>
	<object>
		<name>Limes</name>
		<pose>Unspecified</pose>
		<truncated>0</truncated>
		<difficult>0</difficult>
		<occluded>0</occluded>
		<bndbox>
			<xmin>155</xmin>
			<xmax>304</xmax>
			<ymin>178</ymin>
			<ymax>327</ymax>
		</bndbox>
	</object>
	<object>
		<name>Raspberry</name>
		<pose>Unspecified</pose>
		<truncated>0</truncated>
		<difficult>0</difficult>
		<occluded>0</occluded>
		<bndbox>
			<xmin>344</xmin>
			<xmax>415</xmax>
			<ymin>233</ymin>
			<ymax>304</ymax>
		</bndbox>
	</object>
	<object>
		<name>Kiwi</name>
		<pose>Unspecified</pose>
		<truncated>0</truncated>
		<difficult>0</difficult>
		<occluded>0</occluded>
		<bndbox>
			<xmin>308</xmin>
			<xmax>386</xmax>
			<ymin>234</ymin>
			<ymax>312</ymax>
		</bndbox>
	</object>
</annotation>
