<annotation>
	<folder></folder>
	<filename>2479_jpg.rf.d9c77e71196a313db05f468a0c59cf05.jpg</filename>
	<path>2479_jpg.rf.d9c77e71196a313db05f468a0c59cf05.jpg</path>
	<source>
		<database>roboflow.ai</database>
	</source>
	<size>
		<width>416</width>
		<height>550</height>
		<depth>3</depth>
	</size>
	<segmented>0</segmented>
	<object>
		<name>Passion</name>
		<pose>Unspecified</pose>
		<truncated>0</truncated>
		<difficult>0</difficult>
		<occluded>0</occluded>
		<bndbox>
			<xmin>250</xmin>
			<xmax>302</xmax>
			<ymin>310</ymin>
			<ymax>362</ymax>
		</bndbox>
	</object>
	<object>
		<name>Guava</name>
		<pose>Unspecified</pose>
		<truncated>0</truncated>
		<difficult>0</difficult>
		<occluded>0</occluded>
		<bndbox>
			<xmin>318</xmin>
			<xmax>378</xmax>
			<ymin>276</ymin>
			<ymax>336</ymax>
		</bndbox>
	</object>
	<object>
		<name>Pitahaya</name>
		<pose>Unspecified</pose>
		<truncated>0</truncated>
		<difficult>0</difficult>
		<occluded>0</occluded>
		<bndbox>
			<xmin>52</xmin>
			<xmax>185</xmax>
			<ymin>221</ymin>
			<ymax>354</ymax>
		</bndbox>
	</object>
	<object>
		<name>Pear</name>
		<pose>Unspecified</pose>
		<truncated>0</truncated>
		<difficult>0</difficult>
		<occluded>0</occluded>
		<bndbox>
			<xmin>10</xmin>
			<xmax>140</xmax>
			<ymin>100</ymin>
			<ymax>230</ymax>
		</bndbox>
	</object>
</annotation>
