<annotation>
	<folder></folder>
	<filename>2596_jpg.rf.514121070fca4568ea924c36fc6643b7.jpg</filename>
	<path>2596_jpg.rf.514121070fca4568ea924c36fc6643b7.jpg</path>
	<source>
		<database>roboflow.ai</database>
	</source>
	<size>
		<width>416</width>
		<height>550</height>
		<depth>3</depth>
	</size>
	<segmented>0</segmented>
	<object>
		<name>Cantaloupe</name>
		<pose>Unspecified</pose>
		<truncated>0</truncated>
		<difficult>0</difficult>
		<occluded>0</occluded>
		<bndbox>
			<xmin>101</xmin>
			<xmax>241</xmax>
			<ymin>281</ymin>
			<ymax>421</ymax>
		</bndbox>
	</object>
	<object>
		<name>Plum</name>
		<pose>Unspecified</pose>
		<truncated>0</truncated>
		<difficult>0</difficult>
		<occluded>0</occluded>
		<bndbox>
			<xmin>293</xmin>
			<xmax>401</xmax>
			<ymin>53</ymin>
			<ymax>161</ymax>
		</bndbox>
	</object>
	<object>
		<name>Avocado</name>
		<pose>Unspecified</pose>
		<truncated>0</truncated>
		<difficult>0</difficult>
		<occluded>0</occluded>
		<bndbox>
			<xmin>158</xmin>
			<xmax>280</xmax>
			<ymin>423</ymin>
			<ymax>545</ymax>
		</bndbox>
	</object>
	<object>
		<name>Granadilla</name>
		<pose>Unspecified</pose>
		<truncated>0</truncated>
		<difficult>0</difficult>
		<occluded>0</occluded>
		<bndbox>
			<xmin>155</xmin>
			<xmax>230</xmax>
			<ymin>155</ymin>
			<ymax>230</ymax>
		</bndbox>
	</object>
	<object>
		<name>Peach</name>
		<pose>Unspecified</pose>
		<truncated>0</truncated>
		<difficult>0</difficult>
		<occluded>0</occluded>
		<bndbox>
			<xmin>66</xmin>
			<xmax>155</xmax>
			<ymin>10</ymin>
			<ymax>99</ymax>
		</bndbox>
	</object>
	<object>
		<name>Kaki</name>
		<pose>Unspecified</pose>
		<truncated>0</truncated>
		<difficult>0</difficult>
		<occluded>0</occluded>
		<bndbox>
			<xmin>21</xmin>
			<xmax>169</xmax>
			<ymin>96</ymin>
			<ymax>244</ymax>
		</bndbox>
	</object>
</annotation>
