<annotation>
	<folder></folder>
	<filename>2682_jpg.rf.b7cf297f8596510e5b8b1550b3de258a.jpg</filename>
	<path>2682_jpg.rf.b7cf297f8596510e5b8b1550b3de258a.jpg</path>
	<source>
		<database>roboflow.ai</database>
	</source>
	<size>
		<width>416</width>
		<height>550</height>
		<depth>3</depth>
	</size>
	<segmented>0</segmented>
	<object>
		<name>Peach</name>
		<pose>Unspecified</pose>
		<truncated>0</truncated>
		<difficult>0</difficult>
		<occluded>0</occluded>
		<bndbox>
			<xmin>92</xmin>
			<xmax>236</xmax>
			<ymin>296</ymin>
			<ymax>440</ymax>
		</bndbox>
	</object>
	<object>
		<name>Maracuja</name>
		<pose>Unspecified</pose>
		<truncated>0</truncated>
		<difficult>0</difficult>
		<occluded>0</occluded>
		<bndbox>
			<xmin>119</xmin>
			<xmax>269</xmax>
			<ymin>127</ymin>
			<ymax>277</ymax>
		</bndbox>
	</object>
	<object>
		<name>Cocos</name>
		<pose>Unspecified</pose>
		<truncated>0</truncated>
		<difficult>0</difficult>
		<occluded>0</occluded>
		<bndbox>
			<xmin>22</xmin>
			<xmax>145</xmax>
			<ymin>358</ymin>
			<ymax>481</ymax>
		</bndbox>
	</object>
	<object>
		<name>Maracuja</name>
		<pose>Unspecified</pose>
		<truncated>0</truncated>
		<difficult>0</difficult>
		<occluded>0</occluded>
		<bndbox>
			<xmin>28</xmin>
			<xmax>83</xmax>
			<ymin>267</ymin>
			<ymax>322</ymax>
		</bndbox>
	</object>
	<object>
		<name>Lemon</name>
		<pose>Unspecified</pose>
		<truncated>0</truncated>
		<difficult>0</difficult>
		<occluded>0</occluded>
		<bndbox>
			<xmin>315</xmin>
			<xmax>408</xmax>
			<ymin>119</ymin>
			<ymax>212</ymax>
		</bndbox>
	</object>
</annotation>
