<annotation>
	<folder></folder>
	<filename>2968_jpg.rf.deda81bef1e61f99e2086dd7a8870487.jpg</filename>
	<path>2968_jpg.rf.deda81bef1e61f99e2086dd7a8870487.jpg</path>
	<source>
		<database>roboflow.ai</database>
	</source>
	<size>
		<width>416</width>
		<height>550</height>
		<depth>3</depth>
	</size>
	<segmented>0</segmented>
	<object>
		<name>Pomegranate</name>
		<pose>Unspecified</pose>
		<truncated>0</truncated>
		<difficult>0</difficult>
		<occluded>0</occluded>
		<bndbox>
			<xmin>55</xmin>
			<xmax>178</xmax>
			<ymin>309</ymin>
			<ymax>432</ymax>
		</bndbox>
	</object>
	<object>
		<name>Limes</name>
		<pose>Unspecified</pose>
		<truncated>0</truncated>
		<difficult>0</difficult>
		<occluded>0</occluded>
		<bndbox>
			<xmin>286</xmin>
			<xmax>359</xmax>
			<ymin>418</ymin>
			<ymax>491</ymax>
		</bndbox>
	</object>
	<object>
		<name>Pepper</name>
		<pose>Unspecified</pose>
		<truncated>0</truncated>
		<difficult>0</difficult>
		<occluded>0</occluded>
		<bndbox>
			<xmin>335</xmin>
			<xmax>391</xmax>
			<ymin>14</ymin>
			<ymax>70</ymax>
		</bndbox>
	</object>
</annotation>
