<annotation>
	<folder></folder>
	<filename>3219_jpg.rf.26906b39f9032e8cb4a41a0ce0fdda13.jpg</filename>
	<path>3219_jpg.rf.26906b39f9032e8cb4a41a0ce0fdda13.jpg</path>
	<source>
		<database>roboflow.ai</database>
	</source>
	<size>
		<width>416</width>
		<height>550</height>
		<depth>3</depth>
	</size>
	<segmented>0</segmented>
	<object>
		<name>Pitahaya</name>
		<pose>Unspecified</pose>
		<truncated>0</truncated>
		<difficult>0</difficult>
		<occluded>0</occluded>
		<bndbox>
			<xmin>302</xmin>
			<xmax>413</xmax>
			<ymin>79</ymin>
			<ymax>190</ymax>
		</bndbox>
	</object>
	<object>
		<name>Guava</name>
		<pose>Unspecified</pose>
		<truncated>0</truncated>
		<difficult>0</difficult>
		<occluded>0</occluded>
		<bndbox>
			<xmin>189</xmin>
			<xmax>277</xmax>
			<ymin>459</ymin>
			<ymax>547</ymax>
		</bndbox>
	</object>
</annotation>
