<annotation>
	<folder></folder>
	<filename>3327_jpg.rf.5d910e42569bb4f23a809d90e76dec49.jpg</filename>
	<path>3327_jpg.rf.5d910e42569bb4f23a809d90e76dec49.jpg</path>
	<source>
		<database>roboflow.ai</database>
	</source>
	<size>
		<width>416</width>
		<height>550</height>
		<depth>3</depth>
	</size>
	<segmented>0</segmented>
	<object>
		<name>Onion</name>
		<pose>Unspecified</pose>
		<truncated>0</truncated>
		<difficult>0</difficult>
		<occluded>0</occluded>
		<bndbox>
			<xmin>232</xmin>
			<xmax>345</xmax>
			<ymin>155</ymin>
			<ymax>268</ymax>
		</bndbox>
	</object>
</annotation>
