<annotation>
	<folder></folder>
	<filename>3333_jpg.rf.a706edd04bd7e477fa50c0bdaf08931e.jpg</filename>
	<path>3333_jpg.rf.a706edd04bd7e477fa50c0bdaf08931e.jpg</path>
	<source>
		<database>roboflow.ai</database>
	</source>
	<size>
		<width>416</width>
		<height>550</height>
		<depth>3</depth>
	</size>
	<segmented>0</segmented>
	<object>
		<name>Mangostan</name>
		<pose>Unspecified</pose>
		<truncated>0</truncated>
		<difficult>0</difficult>
		<occluded>0</occluded>
		<bndbox>
			<xmin>116</xmin>
			<xmax>185</xmax>
			<ymin>227</ymin>
			<ymax>296</ymax>
		</bndbox>
	</object>
	<object>
		<name>Plum</name>
		<pose>Unspecified</pose>
		<truncated>0</truncated>
		<difficult>0</difficult>
		<occluded>0</occluded>
		<bndbox>
			<xmin>149</xmin>
			<xmax>290</xmax>
			<ymin>228</ymin>
			<ymax>369</ymax>
		</bndbox>
	</object>
</annotation>
