<annotation>
	<folder></folder>
	<filename>334_jpg.rf.111b544ecddbc6a289d95b87df2d67b8.jpg</filename>
	<path>334_jpg.rf.111b544ecddbc6a289d95b87df2d67b8.jpg</path>
	<source>
		<database>roboflow.ai</database>
	</source>
	<size>
		<width>416</width>
		<height>550</height>
		<depth>3</depth>
	</size>
	<segmented>0</segmented>
	<object>
		<name>Banana</name>
		<pose>Unspecified</pose>
		<truncated>0</truncated>
		<difficult>0</difficult>
		<occluded>0</occluded>
		<bndbox>
			<xmin>120</xmin>
			<xmax>211</xmax>
			<ymin>124</ymin>
			<ymax>215</ymax>
		</bndbox>
	</object>
	<object>
		<name>Maracuja</name>
		<pose>Unspecified</pose>
		<truncated>0</truncated>
		<difficult>0</difficult>
		<occluded>0</occluded>
		<bndbox>
			<xmin>227</xmin>
			<xmax>305</xmax>
			<ymin>305</ymin>
			<ymax>383</ymax>
		</bndbox>
	</object>
</annotation>
