<annotation>
	<folder></folder>
	<filename>3887_jpg.rf.bc3f72ad0e9186b5a98f3adc543f15fc.jpg</filename>
	<path>3887_jpg.rf.bc3f72ad0e9186b5a98f3adc543f15fc.jpg</path>
	<source>
		<database>roboflow.ai</database>
	</source>
	<size>
		<width>416</width>
		<height>550</height>
		<depth>3</depth>
	</size>
	<segmented>0</segmented>
	<object>
		<name>Nectarine</name>
		<pose>Unspecified</pose>
		<truncated>0</truncated>
		<difficult>0</difficult>
		<occluded>0</occluded>
		<bndbox>
			<xmin>260</xmin>
			<xmax>358</xmax>
			<ymin>202</ymin>
			<ymax>300</ymax>
		</bndbox>
	</object>
</annotation>
