<annotation>
	<folder></folder>
	<filename>395_jpg.rf.2a12ce3f6447b1de86c4764d2bf4d299.jpg</filename>
	<path>395_jpg.rf.2a12ce3f6447b1de86c4764d2bf4d299.jpg</path>
	<source>
		<database>roboflow.ai</database>
	</source>
	<size>
		<width>416</width>
		<height>550</height>
		<depth>3</depth>
	</size>
	<segmented>0</segmented>
	<object>
		<name>Nectarine</name>
		<pose>Unspecified</pose>
		<truncated>0</truncated>
		<difficult>0</difficult>
		<occluded>0</occluded>
		<bndbox>
			<xmin>260</xmin>
			<xmax>384</xmax>
			<ymin>392</ymin>
			<ymax>516</ymax>
		</bndbox>
	</object>
	<object>
		<name>Eggplant</name>
		<pose>Unspecified</pose>
		<truncated>0</truncated>
		<difficult>0</difficult>
		<occluded>0</occluded>
		<bndbox>
			<xmin>55</xmin>
			<xmax>134</xmax>
			<ymin>227</ymin>
			<ymax>306</ymax>
		</bndbox>
	</object>
	<object>
		<name>Kohlrabi</name>
		<pose>Unspecified</pose>
		<truncated>0</truncated>
		<difficult>0</difficult>
		<occluded>0</occluded>
		<bndbox>
			<xmin>76</xmin>
			<xmax>201</xmax>
			<ymin>129</ymin>
			<ymax>254</ymax>
		</bndbox>
	</object>
</annotation>
