<annotation>
	<folder></folder>
	<filename>4184_jpg.rf.a56dbb38a7d5ed1ac01e21f931e39339.jpg</filename>
	<path>4184_jpg.rf.a56dbb38a7d5ed1ac01e21f931e39339.jpg</path>
	<source>
		<database>roboflow.ai</database>
	</source>
	<size>
		<width>416</width>
		<height>550</height>
		<depth>3</depth>
	</size>
	<segmented>0</segmented>
	<object>
		<name>Grapefruit</name>
		<pose>Unspecified</pose>
		<truncated>0</truncated>
		<difficult>0</difficult>
		<occluded>0</occluded>
		<bndbox>
			<xmin>155</xmin>
			<xmax>225</xmax>
			<ymin>264</ymin>
			<ymax>334</ymax>
		</bndbox>
	</object>
	<object>
		<name>Tomato</name>
		<pose>Unspecified</pose>
		<truncated>0</truncated>
		<difficult>0</difficult>
		<occluded>0</occluded>
		<bndbox>
			<xmin>179</xmin>
			<xmax>323</xmax>
			<ymin>366</ymin>
			<ymax>510</ymax>
		</bndbox>
	</object>
	<object>
		<name>Cherry</name>
		<pose>Unspecified</pose>
		<truncated>0</truncated>
		<difficult>0</difficult>
		<occluded>0</occluded>
		<bndbox>
			<xmin>148</xmin>
			<xmax>298</xmax>
			<ymin>268</ymin>
			<ymax>418</ymax>
		</bndbox>
	</object>
</annotation>
