<annotation>
	<folder></folder>
	<filename>4267_jpg.rf.ed4ba7d8d7c4a89bea664fe75df191c1.jpg</filename>
	<path>4267_jpg.rf.ed4ba7d8d7c4a89bea664fe75df191c1.jpg</path>
	<source>
		<database>roboflow.ai</database>
	</source>
	<size>
		<width>416</width>
		<height>550</height>
		<depth>3</depth>
	</size>
	<segmented>0</segmented>
	<object>
		<name>Ginger</name>
		<pose>Unspecified</pose>
		<truncated>0</truncated>
		<difficult>0</difficult>
		<occluded>0</occluded>
		<bndbox>
			<xmin>102</xmin>
			<xmax>224</xmax>
			<ymin>198</ymin>
			<ymax>320</ymax>
		</bndbox>
	</object>
</annotation>
