<annotation>
	<folder></folder>
	<filename>446_jpg.rf.66d8064aecdd357b8e11a5e1922581b5.jpg</filename>
	<path>446_jpg.rf.66d8064aecdd357b8e11a5e1922581b5.jpg</path>
	<source>
		<database>roboflow.ai</database>
	</source>
	<size>
		<width>416</width>
		<height>550</height>
		<depth>3</depth>
	</size>
	<segmented>0</segmented>
	<object>
		<name>Ginger</name>
		<pose>Unspecified</pose>
		<truncated>0</truncated>
		<difficult>0</difficult>
		<occluded>0</occluded>
		<bndbox>
			<xmin>273</xmin>
			<xmax>352</xmax>
			<ymin>375</ymin>
			<ymax>454</ymax>
		</bndbox>
	</object>
	<object>
		<name>Kohlrabi</name>
		<pose>Unspecified</pose>
		<truncated>0</truncated>
		<difficult>0</difficult>
		<occluded>0</occluded>
		<bndbox>
			<xmin>157</xmin>
			<xmax>234</xmax>
			<ymin>135</ymin>
			<ymax>212</ymax>
		</bndbox>
	</object>
	<object>
		<name>Maracuja</name>
		<pose>Unspecified</pose>
		<truncated>0</truncated>
		<difficult>0</difficult>
		<occluded>0</occluded>
		<bndbox>
			<xmin>182</xmin>
			<xmax>321</xmax>
			<ymin>100</ymin>
			<ymax>239</ymax>
		</bndbox>
	</object>
</annotation>
