<annotation>
	<folder></folder>
	<filename>4600_jpg.rf.0762c4dbb5ac8484a6236723da48d467.jpg</filename>
	<path>4600_jpg.rf.0762c4dbb5ac8484a6236723da48d467.jpg</path>
	<source>
		<database>roboflow.ai</database>
	</source>
	<size>
		<width>416</width>
		<height>550</height>
		<depth>3</depth>
	</size>
	<segmented>0</segmented>
	<object>
		<name>Mandarine</name>
		<pose>Unspecified</pose>
		<truncated>0</truncated>
		<difficult>0</difficult>
		<occluded>0</occluded>
		<bndbox>
			<xmin>266</xmin>
			<xmax>322</xmax>
			<ymin>435</ymin>
			<ymax>491</ymax>
		</bndbox>
	</object>
	<object>
		<name>Plum</name>
		<pose>Unspecified</pose>
		<truncated>0</truncated>
		<difficult>0</difficult>
		<occluded>0</occluded>
		<bndbox>
			<xmin>271</xmin>
			<xmax>396</xmax>
			<ymin>223</ymin>
			<ymax>348</ymax>
		</bndbox>
	</object>
</annotation>
