<annotation>
	<folder></folder>
	<filename>4960_jpg.rf.fd74d467d1efa30365c3c2cb44cf54f9.jpg</filename>
	<path>4960_jpg.rf.fd74d467d1efa30365c3c2cb44cf54f9.jpg</path>
	<source>
		<database>roboflow.ai</database>
	</source>
	<size>
		<width>416</width>
		<height>550</height>
		<depth>3</depth>
	</size>
	<segmented>0</segmented>
	<object>
		<name>Quince</name>
		<pose>Unspecified</pose>
		<truncated>0</truncated>
		<difficult>0</difficult>
		<occluded>0</occluded>
		<bndbox>
			<xmin>80</xmin>
			<xmax>226</xmax>
			<ymin>349</ymin>
			<ymax>495</ymax>
		</bndbox>
	</object>
	<object>
		<name>Huckleberry</name>
		<pose>Unspecified</pose>
		<truncated>0</truncated>
		<difficult>0</difficult>
		<occluded>0</occluded>
		<bndbox>
			<xmin>255</xmin>
			<xmax>361</xmax>
			<ymin>158</ymin>
			<ymax>264</ymax>
		</bndbox>
	</object>
</annotation>
