<annotation>
	<folder></folder>
	<filename>4964_jpg.rf.9e0edb615b0e5d803d9edd6122b1a9e4.jpg</filename>
	<path>4964_jpg.rf.9e0edb615b0e5d803d9edd6122b1a9e4.jpg</path>
	<source>
		<database>roboflow.ai</database>
	</source>
	<size>
		<width>416</width>
		<height>550</height>
		<depth>3</depth>
	</size>
	<segmented>0</segmented>
	<object>
		<name>Banana</name>
		<pose>Unspecified</pose>
		<truncated>0</truncated>
		<difficult>0</difficult>
		<occluded>0</occluded>
		<bndbox>
			<xmin>221</xmin>
			<xmax>347</xmax>
			<ymin>256</ymin>
			<ymax>382</ymax>
		</bndbox>
	</object>
</annotation>
